<?xml version="1.0"?>
<cena version="0.8.2"><result judgetime="41505.644480081"><problem title="&#x7D2F;&#x52A0;" filename="1.pas" status="1" hash="2501980932" detail=""><testcase status="7" exitcode="0" detail="" time="0" memory="792" score="10"/><testcase status="7" exitcode="0" detail="" time="0" memory="788" score="10"/></problem><problem title="&#x4E58;&#x6CD5;" filename="2.pas" status="1" hash="4220801963" detail=""><testcase status="7" exitcode="0" detail="&#x8FD9;&#x4E2A;&#x6D4B;&#x8BD5;&#x70B9;&#x7684;&#x8F93;&#x5165;&#x4E3A;&#xFF1A;11 22&#13;&#10;&#x6807;&#x51C6;&#x8F93;&#x51FA;&#x4E3A;&#xFF1A;242&#13;&#10;&#x9009;&#x624B;&#x8F93;&#x51FA;&#x4E3A;&#xFF1A;242&#13;&#10;&#x6B63;&#x786E;&#x3002;&#13;&#10;&#x672C;&#x6821;&#x9A8C;&#x7A0B;&#x5E8F;&#x7531; *** &#x63D0;&#x4F9B;&#x3002;&#x4EC5;&#x4F9B;&#x793A;&#x4F8B;&#x3002;&#13;&#10;" time="0" memory="788" score="10"/><testcase status="7" exitcode="0" detail="&#x8FD9;&#x4E2A;&#x6D4B;&#x8BD5;&#x70B9;&#x7684;&#x8F93;&#x5165;&#x4E3A;&#xFF1A;111 222&#13;&#10;&#x6807;&#x51C6;&#x8F93;&#x51FA;&#x4E3A;&#xFF1A;24,642&#13;&#10;&#x9009;&#x624B;&#x8F93;&#x51FA;&#x4E3A;&#xFF1A;24,642&#13;&#10;&#x6B63;&#x786E;&#x3002;&#13;&#10;&#x672C;&#x6821;&#x9A8C;&#x7A0B;&#x5E8F;&#x7531; *** &#x63D0;&#x4F9B;&#x3002;&#x4EC5;&#x4F9B;&#x793A;&#x4F8B;&#x3002;&#13;&#10;" time="0" memory="788" score="10"/><testcase status="7" exitcode="0" detail="&#x8FD9;&#x4E2A;&#x6D4B;&#x8BD5;&#x70B9;&#x7684;&#x8F93;&#x5165;&#x4E3A;&#xFF1A;12345 67890&#13;&#10;&#x6807;&#x51C6;&#x8F93;&#x51FA;&#x4E3A;&#xFF1A;838,102,050&#13;&#10;&#x9009;&#x624B;&#x8F93;&#x51FA;&#x4E3A;&#xFF1A;838,102,050&#13;&#10;&#x6B63;&#x786E;&#x3002;&#13;&#10;&#x672C;&#x6821;&#x9A8C;&#x7A0B;&#x5E8F;&#x7531; *** &#x63D0;&#x4F9B;&#x3002;&#x4EC5;&#x4F9B;&#x793A;&#x4F8B;&#x3002;&#13;&#10;" time="0" memory="788" score="10"/><testcase status="7" exitcode="0" detail="&#x8FD9;&#x4E2A;&#x6D4B;&#x8BD5;&#x70B9;&#x7684;&#x8F93;&#x5165;&#x4E3A;&#xFF1A;1234567 1234567&#13;&#10;&#x6807;&#x51C6;&#x8F93;&#x51FA;&#x4E3A;&#xFF1A;1,524,155,677,489&#13;&#10;&#x9009;&#x624B;&#x8F93;&#x51FA;&#x4E3A;&#xFF1A;1,524,155,677,489&#13;&#10;&#x6B63;&#x786E;&#x3002;&#13;&#10;&#x672C;&#x6821;&#x9A8C;&#x7A0B;&#x5E8F;&#x7531; *** &#x63D0;&#x4F9B;&#x3002;&#x4EC5;&#x4F9B;&#x793A;&#x4F8B;&#x3002;&#13;&#10;" time="0.01" memory="788" score="10"/><testcase status="7" exitcode="0" detail="&#x8FD9;&#x4E2A;&#x6D4B;&#x8BD5;&#x70B9;&#x7684;&#x8F93;&#x5165;&#x4E3A;&#xFF1A;999999999 999999999&#13;&#10;&#x6807;&#x51C6;&#x8F93;&#x51FA;&#x4E3A;&#xFF1A;999,999,998,000,000,001&#13;&#10;&#x9009;&#x624B;&#x8F93;&#x51FA;&#x4E3A;&#xFF1A;999,999,998,000,000,001&#13;&#10;&#x6B63;&#x786E;&#x3002;&#13;&#10;&#x672C;&#x6821;&#x9A8C;&#x7A0B;&#x5E8F;&#x7531; *** &#x63D0;&#x4F9B;&#x3002;&#x4EC5;&#x4F9B;&#x793A;&#x4F8B;&#x3002;&#13;&#10;" time="0" memory="784" score="10"/></problem><problem title="&#x6392;&#x5E8F;" filename="3.pas" status="1" hash="2164981056" detail=""><testcase status="9" exitcode="0" detail="&#x53EF;&#x4EE5;&#x63A5;&#x53D7;&#x7684;&#x9519;&#x8BEF;&#xFF0C;&#x5F97;&#x90E8;&#x5206;&#x5206;&#13;&#10;&#x9519;&#x8BEF;&#x5982;&#x4E0B;&#xFF08;&#x5171;2&#x5904;&#xFF09;&#xFF1A;&#13;&#10; --- &#x7B2C;1&#x4E2A;&#x6570;&#x5E94;&#x8BE5;&#x662F;&#xFF1A;4101 --- &#x800C;&#x7A0B;&#x5E8F;&#x8F93;&#x51FA;&#x7684;&#x662F;&#xFF1A;28177&#13;&#10; --- &#x7B2C;10&#x4E2A;&#x6570;&#x5E94;&#x8BE5;&#x662F;&#xFF1A;28177 --- &#x800C;&#x7A0B;&#x5E8F;&#x8F93;&#x51FA;&#x7684;&#x662F;&#xFF1A;4101&#13;&#10;" time="0" memory="804" score="8"/><testcase status="9" exitcode="0" detail="&#x53EF;&#x4EE5;&#x63A5;&#x53D7;&#x7684;&#x9519;&#x8BEF;&#xFF0C;&#x5F97;&#x90E8;&#x5206;&#x5206;&#13;&#10;&#x9519;&#x8BEF;&#x5982;&#x4E0B;&#xFF08;&#x5171;2&#x5904;&#xFF09;&#xFF1A;&#13;&#10; --- &#x7B2C;1&#x4E2A;&#x6570;&#x5E94;&#x8BE5;&#x662F;&#xFF1A;11 --- &#x800C;&#x7A0B;&#x5E8F;&#x8F93;&#x51FA;&#x7684;&#x662F;&#xFF1A;29572&#13;&#10; --- &#x7B2C;100&#x4E2A;&#x6570;&#x5E94;&#x8BE5;&#x662F;&#xFF1A;29572 --- &#x800C;&#x7A0B;&#x5E8F;&#x8F93;&#x51FA;&#x7684;&#x662F;&#xFF1A;11&#13;&#10;" time="0" memory="796" score="8"/><testcase status="9" exitcode="0" detail="&#x53EF;&#x4EE5;&#x63A5;&#x53D7;&#x7684;&#x9519;&#x8BEF;&#xFF0C;&#x5F97;&#x90E8;&#x5206;&#x5206;&#13;&#10;&#x9519;&#x8BEF;&#x5982;&#x4E0B;&#xFF08;&#x5171;2&#x5904;&#xFF09;&#xFF1A;&#13;&#10; --- &#x7B2C;1&#x4E2A;&#x6570;&#x5E94;&#x8BE5;&#x662F;&#xFF1A;81 --- &#x800C;&#x7A0B;&#x5E8F;&#x8F93;&#x51FA;&#x7684;&#x662F;&#xFF1A;29980&#13;&#10; --- &#x7B2C;1000&#x4E2A;&#x6570;&#x5E94;&#x8BE5;&#x662F;&#xFF1A;29980 --- &#x800C;&#x7A0B;&#x5E8F;&#x8F93;&#x51FA;&#x7684;&#x662F;&#xFF1A;81&#13;&#10;" time="0.03" memory="796" score="8"/><testcase status="9" exitcode="0" detail="&#x53EF;&#x4EE5;&#x63A5;&#x53D7;&#x7684;&#x9519;&#x8BEF;&#xFF0C;&#x5F97;&#x90E8;&#x5206;&#x5206;&#13;&#10;&#x9519;&#x8BEF;&#x5982;&#x4E0B;&#xFF08;&#x5171;2&#x5904;&#xFF09;&#xFF1A;&#13;&#10; --- &#x7B2C;1&#x4E2A;&#x6570;&#x5E94;&#x8BE5;&#x662F;&#xFF1A;18 --- &#x800C;&#x7A0B;&#x5E8F;&#x8F93;&#x51FA;&#x7684;&#x662F;&#xFF1A;29994&#13;&#10; --- &#x7B2C;2000&#x4E2A;&#x6570;&#x5E94;&#x8BE5;&#x662F;&#xFF1A;29994 --- &#x800C;&#x7A0B;&#x5E8F;&#x8F93;&#x51FA;&#x7684;&#x662F;&#xFF1A;18&#13;&#10;" time="0.03" memory="800" score="8"/><testcase status="9" exitcode="0" detail="&#x53EF;&#x4EE5;&#x63A5;&#x53D7;&#x7684;&#x9519;&#x8BEF;&#xFF0C;&#x5F97;&#x90E8;&#x5206;&#x5206;&#13;&#10;&#x9519;&#x8BEF;&#x5982;&#x4E0B;&#xFF08;&#x5171;2&#x5904;&#xFF09;&#xFF1A;&#13;&#10; --- &#x7B2C;1&#x4E2A;&#x6570;&#x5E94;&#x8BE5;&#x662F;&#xFF1A;5 --- &#x800C;&#x7A0B;&#x5E8F;&#x8F93;&#x51FA;&#x7684;&#x662F;&#xFF1A;29999&#13;&#10; --- &#x7B2C;5000&#x4E2A;&#x6570;&#x5E94;&#x8BE5;&#x662F;&#xFF1A;29999 --- &#x800C;&#x7A0B;&#x5E8F;&#x8F93;&#x51FA;&#x7684;&#x662F;&#xFF1A;5&#13;&#10;" time="0.1" memory="800" score="8"/></problem><problem title="&#x6392;&#x5E8F;(&#x4F7F;&#x7528;&#x4EA4;&#x4E92;&#x5E93;)" filename="" status="14" hash="0" detail=""><testcase status="14" exitcode="0" detail="" time="0" memory="0" score="0"/><testcase status="14" exitcode="0" detail="" time="0" memory="0" score="0"/><testcase status="14" exitcode="0" detail="" time="0" memory="0" score="0"/><testcase status="14" exitcode="0" detail="" time="0" memory="0" score="0"/><testcase status="14" exitcode="0" detail="" time="0" memory="0" score="0"/></problem></result></cena>
